armisticeai-0.0.5.dist-info/METADATA
armisticeai-0.0.5.dist-info/WHEEL
armisticeai/_cli.py
armisticeai/_train.py
armisticeai/_oldclient.py
armisticeai/_client.py
armisticeai/_dap.py
armisticeai/__init__.py
armisticeai/_dataset.py
armisticeai/_exceptions.py
armisticeai/_preprocess.py
armisticeai/__main__.py
armisticeai/_admin.py
armisticeai/_utils.py
armisticeai/armisticeai.cpython-312-arm-linux-gnueabihf.so
armisticeai-0.0.5.dist-info/RECORD
