Metadata-Version: 2.3
Name: armisticeai
Version: 0.0.5
Classifier: Programming Language :: Rust
Classifier: Programming Language :: Python :: Implementation :: CPython
Classifier: Programming Language :: Python :: Implementation :: PyPy
Author-email: ArmisticeAI <tanya@armistice.ai>
Requires-Python: >=3.8
